vfx_mcp/__init__.py
vfx_mcp/core/__init__.py
vfx_mcp/core/server.py
vfx_mcp/core/utilities.py
vfx_mcp/core/validation.py
vfx_mcp/resources/__init__.py
vfx_mcp/resources/mcp_endpoints.py
vfx_mcp/tools/__init__.py
vfx_mcp/tools/advanced_compositing.py
vfx_mcp/tools/audio_processing.py
vfx_mcp/tools/basic_video_ops.py
vfx_mcp/tools/batch_automation.py
vfx_mcp/tools/format_conversion.py
vfx_mcp/tools/text_animation.py
vfx_mcp/tools/video_analysis.py
vfx_mcp/tools/video_effects.py
vfx_mcp/tools/video_transitions.py
vfx_mcp-0.1.0.dist-info/METADATA
vfx_mcp-0.1.0.dist-info/WHEEL
vfx_mcp-0.1.0.dist-info/entry_points.txt
vfx_mcp-0.1.0.dist-info/licenses/LICENSE
vfx_mcp-0.1.0.dist-info/RECORD
