Metadata-Version: 2.4
Name: vfx-mcp
Version: 0.1.0
Summary: Video editing MCP server using FastMCP and ffmpeg-python
Project-URL: Homepage, https://github.com/conneroisu/vfx-mcp
Project-URL: Repository, https://github.com/conneroisu/vfx-mcp
Project-URL: Documentation, https://github.com/conneroisu/vfx-mcp#readme
Project-URL: Issues, https://github.com/conneroisu/vfx-mcp/issues
Author-email: Conner Ohnesorge <conneroisu@outlook.com>
Maintainer-email: Conner Ohnesorge <conneroisu@outlook.com>
License: MIT
License-File: LICENSE
Keywords: ai,automation,ffmpeg,mcp,video-editing
Classifier: Development Status :: 3 - Alpha
Classifier: Framework :: FastAPI
Classifier: Intended Audience :: Developers
Classifier: License :: OSI Approved :: MIT License
Classifier: Programming Language :: Python :: 3
Classifier: Programming Language :: Python :: 3.13
Classifier: Topic :: Multimedia :: Video
Classifier: Topic :: Software Development :: Libraries :: Python Modules
Requires-Python: >=3.13
Requires-Dist: fastmcp>=2.9.0
Requires-Dist: ffmpeg-python>=0.2.0
Provides-Extra: dev
Requires-Dist: mypy>=1.0.0; extra == 'dev'
Requires-Dist: numpy>=1.24.0; extra == 'dev'
Requires-Dist: pytest-asyncio>=0.21.0; extra == 'dev'
Requires-Dist: pytest-cov>=4.0.0; extra == 'dev'
Requires-Dist: pytest>=7.0.0; extra == 'dev'
Requires-Dist: ruff>=0.1.0; extra == 'dev'
